kickoff_epl/__init__.py
kickoff_epl/__main__.py
kickoff_epl/assets/2009-10.csv
kickoff_epl/assets/2010-11.csv
kickoff_epl/assets/2011-12.csv
kickoff_epl/assets/2012-13.csv
kickoff_epl/assets/2013-14.csv
kickoff_epl/assets/2014-15.csv
kickoff_epl/assets/2015-16.csv
kickoff_epl/assets/2016-17.csv
kickoff_epl/assets/2017-18.csv
kickoff_epl/assets/2018-19.csv
kickoff_epl/assets/__init__.py
kickoff_epl/cmd/__init__.py
kickoff_epl/cmd/commands.py
kickoff_epl/cmd/output.py
kickoff_epl/cmd/validation.py
kickoff_epl/controllers/aggregation.py
kickoff_epl/controllers/optimization.py
kickoff_epl/controllers/predictions.py
kickoff_epl/controllers/records.py
kickoff_epl/main.py
kickoff_epl/models/__init__.py
kickoff_epl/models/league.py
kickoff_epl/models/match.py
kickoff_epl/models/team.py
kickoff_epl/utils/__init__.py
kickoff_epl/utils/constants.py
kickoff_epl/utils/helpers.py
kickoff_epl/utils/load.py
kickoff_epl-0.1.1.dist-info/METADATA
kickoff_epl-0.1.1.dist-info/WHEEL
kickoff_epl-0.1.1.dist-info/entry_points.txt
kickoff_epl-0.1.1.dist-info/RECORD
