Metadata-Version: 2.1
Name: kickoff-epl
Version: 0.1.1
Summary: 
Author: Harshith
Author-email: harshithl1777@gmail.com
Requires-Python: >=3.11,<4.0
Classifier: Programming Language :: Python :: 3
Classifier: Programming Language :: Python :: 3.11
Requires-Dist: numpy (==1.24.1)
Requires-Dist: pandas (>=2.0.0,<3.0.0)
Requires-Dist: typer[all] (>=0.7.0,<0.8.0)
